{"dataset_func_kwargs": {"UkAir": {"func_name": "UkAir", "kwargs": {}}}, "encoder_func_kwargs": {"OneHotEncoder": {"func_name": "OneHotEncoder", "kwargs": {}}, "OrdinalEncoder": {"func_name": "OrdinalEncoder", "kwargs": {}}, "CountEncoder": {"func_name": "CountEncoder", "kwargs": {}}, "BaseNEncoder": {"func_name": "BaseNEncoder", "kwargs": {}}, "BackwardDifferenceEncoder": {"func_name": "BackwardDifferenceEncoder", "kwargs": {}}, "HelmertEncoder": {"func_name": "HelmertEncoder", "kwargs": {}}, "SumEncoder": {"func_name": "SumEncoder", "kwargs": {}}, "MinHashEncoder": {"func_name": "MinHashEncoder", "kwargs": {}}, "SimilarityEncoder": {"func_name": "SimilarityEncoder", "kwargs": {}}, "TargetEncoder": {"func_name": "TargetEncoder", "kwargs": {}}, "WOEEncoder": {"func_name": "WOEEncoder", "kwargs": {}}, "JamesSteinEncoder": {"func_name": "JamesSteinEncoder", "kwargs": {}}, "MEstimateEncoder": {"func_name": "MEstimateEncoder", "kwargs": {}}, "QuantileEncoder": {"func_name": "QuantileEncoder", "kwargs": {}}, "MeanEncoder": {"func_name": "MeanEncoder", "kwargs": {}}, "GLMMEncoder": {"func_name": "GLMMEncoder", "kwargs": {}}, "DeleteEncoder": {"func_name": "DeleteEncoder", "kwargs": {}}}, "model_func_kwargs": {"MLPClassifier": {"func_name": "MLPClassifier", "kwargs": {}}, "RandomForestClassifier": {"func_name": "RandomForestClassifier", "kwargs": {}}, "DecisionTreeClassifier": {"func_name": "DecisionTreeClassifier", "kwargs": {"max_depth": 10, "min_samples_leaf": 10}}, "XGBClassifier": {"func_name": "XGBClassifier", "kwargs": {"tree_method": "hist", "enable_categorical": true}}, "LGBMClassifier": {"func_name": "LGBMClassifier", "kwargs": {}}, "MLPRegressor": {"func_name": "MLPRegressor", "kwargs": {}}, "RandomForestRegressor": {"func_name": "RandomForestRegressor", "kwargs": {}}, "LogisticRegression": {"func_name": "LogisticRegression", "kwargs": {}}, "RidgeCV": {"func_name": "RidgeCV", "kwargs": {}}, "DecisionTreeRegressor": {"func_name": "DecisionTreeRegressor", "kwargs": {"max_depth": 10, "min_samples_leaf": 10}}, "XGBRegressor": {"func_name": "XGBRegressor", "kwargs": {"tree_method": "hist", "enable_categorical": true}}, "LGBMRegressor": {"func_name": "LGBMRegressor", "kwargs": {}}, "LinearSVR": {"func_name": "LinearSVR", "kwargs": {}}, "LinearSVC": {"func_name": "LinearSVC", "kwargs": {}}}, "other_kwargs": {"seeds": [4, 5, 6], "output_dir": "../output/result/20240104_ukair_msidown1/", "test_size": 0.2, "use_cache": false, "delete_highest": false}}